vitruvi/__init__.py
vitruvi/client.py
vitruvi/core/__init__.py
vitruvi/core/api_error.py
vitruvi/core/datetime_utils.py
vitruvi/core/jsonable_encoder.py
vitruvi/core/remove_none_from_headers.py
vitruvi/errors/__init__.py
vitruvi/errors/bad_request_error.py
vitruvi/errors/not_found_error.py
vitruvi/py.typed
vitruvi/resources/__init__.py
vitruvi/resources/auth/__init__.py
vitruvi/resources/auth/client.py
vitruvi/resources/global_configuration/__init__.py
vitruvi/resources/global_configuration/client.py
vitruvi/resources/jobs/__init__.py
vitruvi/resources/jobs/client.py
vitruvi/resources/reporting/__init__.py
vitruvi/resources/reporting/client.py
vitruvi/types/__init__.py
vitruvi/types/account.py
vitruvi/types/accounts_payable_item_export.py
vitruvi/types/accounts_receivable_item_export.py
vitruvi/types/async_api_result.py
vitruvi/types/company.py
vitruvi/types/company_type_enum.py
vitruvi/types/crew_export.py
vitruvi/types/crew_member_export.py
vitruvi/types/custom_field_settings_export.py
vitruvi/types/design_element_export.py
vitruvi/types/design_export.py
vitruvi/types/error_message.py
vitruvi/types/full_crew_person_role.py
vitruvi/types/global_configuration_list_v_1_companies_request_type.py
vitruvi/types/invoice_export.py
vitruvi/types/paginated_accounts_payable_item_export_list.py
vitruvi/types/paginated_accounts_receivable_item_export_list.py
vitruvi/types/paginated_company_list.py
vitruvi/types/paginated_crew_export_list.py
vitruvi/types/paginated_crew_member_export_list.py
vitruvi/types/paginated_custom_field_settings_export_list.py
vitruvi/types/paginated_design_element_export_list.py
vitruvi/types/paginated_design_export_list.py
vitruvi/types/paginated_invoice_export_list.py
vitruvi/types/paginated_permission_list.py
vitruvi/types/paginated_production_report_export_list.py
vitruvi/types/paginated_production_report_line_export_list.py
vitruvi/types/paginated_production_report_quantity_export_list.py
vitruvi/types/paginated_profile_export_list.py
fern_vitruvi-0.0.6.dist-info/METADATA
fern_vitruvi-0.0.6.dist-info/WHEEL
fern_vitruvi-0.0.6.dist-info/RECORD
